UnleashClient/__init__.py
UnleashClient/constants.py
UnleashClient/deprecation_warnings.py
UnleashClient/loader.py
UnleashClient/utils.py
UnleashClient/api/__init__.py
UnleashClient/api/features.py
UnleashClient/api/metrics.py
UnleashClient/api/register.py
UnleashClient/constraints/Constraint.py
UnleashClient/constraints/__init__.py
UnleashClient/features/Feature.py
UnleashClient/features/__init__.py
UnleashClient/periodic_tasks/__init__.py
UnleashClient/periodic_tasks/fetch_and_load.py
UnleashClient/periodic_tasks/send_metrics.py
UnleashClient/strategies/ApplicationHostname.py
UnleashClient/strategies/Default.py
UnleashClient/strategies/FlexibleRolloutStrategy.py
UnleashClient/strategies/GradualRolloutRandom.py
UnleashClient/strategies/GradualRolloutSessionId.py
UnleashClient/strategies/GradualRolloutUserId.py
UnleashClient/strategies/RemoteAddress.py
UnleashClient/strategies/Strategy.py
UnleashClient/strategies/UserWithId.py
UnleashClient/strategies/__init__.py
UnleashClient/variants/Variants.py
UnleashClient/variants/__init__.py
tests/__init__.py
tests/specification_tests/__init__.py
tests/specification_tests/test_01_simple_examples.py
tests/specification_tests/test_02_user_with_id_strategy.py
tests/specification_tests/test_03_gradual_rollout_user_id_strategy.py
tests/specification_tests/test_04_gradual_rollout_session_id_strategy.py
tests/specification_tests/test_05_gradual_rollout_random_strategy.py
tests/specification_tests/test_06_remote_address_strategy.py
tests/specification_tests/test_07_multiple_strategies.py
tests/specification_tests/test_08_variants.py
tests/specification_tests/test_09_strategy_constraints.py
tests/specification_tests/test_10_flexible_rollout.py
tests/unit_tests/__init__.py
tests/unit_tests/test_client.py
tests/unit_tests/test_constraints.py
tests/unit_tests/test_custom_strategy.py
tests/unit_tests/test_features.py
tests/unit_tests/test_loader.py
tests/unit_tests/test_variants.py
tests/unit_tests/api/__init__.py
asen_UnleashClient-3.4.3.dist-info/LICENSE.md
asen_UnleashClient-3.4.3.dist-info/METADATA
asen_UnleashClient-3.4.3.dist-info/WHEEL
asen_UnleashClient-3.4.3.dist-info/top_level.txt
asen_UnleashClient-3.4.3.dist-info/RECORD
