Metadata-Version: 2.1
Name: asen-UnleashClient
Version: 3.4.3
Summary: Python client for the Unleash feature toggle system!
Home-page: https://github.com/Unleash/unleash-client-python
Author: Ivan Lee
Author-email: ivanklee86@gmail.com
License: UNKNOWN
Platform: UNKNOWN
Classifier: Development Status :: 5 - Production/Stable
Classifier: Intended Audience :: Developers
Classifier: License :: OSI Approved :: MIT License
Classifier: Programming Language :: Python :: 3.5
Classifier: Programming Language :: Python :: 3.6
Classifier: Programming Language :: Python :: 3.7
Classifier: Programming Language :: Python :: 3.8
Requires-Dist: requests (==2.24.0)
Requires-Dist: fcache (==0.4.7)
Requires-Dist: mmh3 (==2.5.1)
Requires-Dist: apscheduler (==3.6.3)
